jisho_scraper/__init__.py
jisho_scraper/anki_connect_client.py
jisho_scraper/anki_exporter.py
jisho_scraper/cli_exporter.py
jisho_scraper/csv_exporter.py
jisho_scraper/jisho_client.py
jisho_scraper/jisho_data.py
jisho_scraper/main.py
jisho_scraper/output_prepare.py
jisho_scraper-1.1.0.dist-info/LICENSE
jisho_scraper-1.1.0.dist-info/METADATA
jisho_scraper-1.1.0.dist-info/WHEEL
jisho_scraper-1.1.0.dist-info/entry_points.txt
jisho_scraper-1.1.0.dist-info/top_level.txt
jisho_scraper-1.1.0.dist-info/RECORD
